kanban_cli/__init__.py
kanban_cli/app/__init__.py
kanban_cli/app/app.py
kanban_cli/app/models.py
kanban_cli/categories/__init__.py
kanban_cli/categories/categories_app.py
kanban_cli/categories/controllers/__init__.py
kanban_cli/categories/controllers/add_controller.py
kanban_cli/categories/controllers/delete_controller.py
kanban_cli/categories/controllers/edit_controller.py
kanban_cli/categories/controllers/view_all_controller.py
kanban_cli/categories/models/__init__.py
kanban_cli/categories/models/category.py
kanban_cli/categories/presenters/__init__.py
kanban_cli/categories/presenters/cannot_delete_category_presenter.py
kanban_cli/categories/presenters/no_categories_presenter.py
kanban_cli/categories/presenters/no_category_presenter.py
kanban_cli/categories/presenters/view_all_presenter.py
kanban_cli/config.py
kanban_cli/settings.toml
kanban_cli/tasks/__init__.py
kanban_cli/tasks/controllers/__init__.py
kanban_cli/tasks/controllers/add_controller.py
kanban_cli/tasks/controllers/delete_controller.py
kanban_cli/tasks/controllers/edit_controller.py
kanban_cli/tasks/controllers/promote_controller.py
kanban_cli/tasks/controllers/regress_controller.py
kanban_cli/tasks/controllers/view_all_controller.py
kanban_cli/tasks/controllers/view_controller.py
kanban_cli/tasks/models/__init__.py
kanban_cli/tasks/models/task.py
kanban_cli/tasks/presenters/__init__.py
kanban_cli/tasks/presenters/no_task_presenter.py
kanban_cli/tasks/presenters/no_tasks_presenter.py
kanban_cli/tasks/presenters/view_all_presenter.py
kanban_cli/tasks/presenters/view_presenter.py
kanban_cli/tasks/prompts/__init__.py
kanban_cli/tasks/prompts/category_prompt.py
kanban_cli/tasks/prompts/confirm_prompt.py
kanban_cli/tasks/prompts/details_prompt.py
kanban_cli/tasks/prompts/priority_prompt.py
kanban_cli/tasks/prompts/status_prompt.py
kanban_cli/tasks/prompts/title_prompt.py
kanban_cli/tasks/tasks_app.py
py_kanban_cli-0.1.4.dist-info/WHEEL
py_kanban_cli-0.1.4.dist-info/entry_points.txt
py_kanban_cli-0.1.4.dist-info/METADATA
py_kanban_cli-0.1.4.dist-info/RECORD
