Metadata-Version: 2.3
Name: py-kanban-cli
Version: 0.1.4
Summary: Personal kanban management in command line
Author: Fillipe Goulart
Author-email: Fillipe Goulart <fillipe.gsm@tutanota.com>
Requires-Dist: dynaconf>=3.2.11
Requires-Dist: peewee>=3.18.2
Requires-Dist: prompt-toolkit>=3.0.52
Requires-Dist: rich>=14.1.0
Requires-Dist: typer>=0.19.2
Requires-Python: >=3.9
Project-URL: Homepage, https://github.com/fillipe-gsm/kanban-cli
Project-URL: Issues, https://github.com/fillipe-gsm/kanban-cli/issues
Project-URL: Repository, https://github.com/fillipe-gsm/kanban-cli
